functions_pkg/__init__.py
functions_pkg/stats_functions.py
functions_pkg/supervised_regression.py
ds_functions_pkg-0.3.0.dist-info/LICENSE
ds_functions_pkg-0.3.0.dist-info/METADATA
ds_functions_pkg-0.3.0.dist-info/WHEEL
ds_functions_pkg-0.3.0.dist-info/top_level.txt
ds_functions_pkg-0.3.0.dist-info/RECORD
