Metadata-Version: 2.1
Name: ds-functions-pkg
Version: 0.3.0
Summary: useful data science functions
Home-page: https://github.com/taylor-m/ds_functions_pkg
Author: Taylor Martin
Author-email: taymart@gmail.com
License: MIT
Platform: UNKNOWN
